{
  "/Users/eunchae/.Trash": 0,
  "/Users/eunchae/.cups": 29,
  "/Users/eunchae/.idlerc": 1069,
  "/Users/eunchae/.ipython": 29043,
  "/Users/eunchae/.matplotlib": 145512,
  "/Users/eunchae/.ssh": 2966,
  "/Users/eunchae/.vnc": 34520,
  "/Users/eunchae/.vscode": 180953993,
  "/Users/eunchae/.wingpersonal10": 505424,
  "/Users/eunchae/.wizvera": 5589,
  "/Users/eunchae/.zsh_sessions": 46169,
  "/Users/eunchae/Applications": 10532938,
  "/Users/eunchae/Desktop": 1082048676,
  "/Users/eunchae/Documents": 145757057,
  "/Users/eunchae/Downloads": 13671114483,
  "/Users/eunchae/Library": 33290438223,
  "/Users/eunchae/Movies": 128541030,
  "/Users/eunchae/Music": 4737299,
  "/Users/eunchae/Pictures": 343394886,
  "/Users/eunchae/Public": 6148,
  "/Users/eunchae/Purdue": 2780912387
}